ddd_value_objects/__init__.py
ddd_value_objects/bool_value_object.py
ddd_value_objects/composite_value_object.py
ddd_value_objects/country_code_value_object.py
ddd_value_objects/currency_value_object.py
ddd_value_objects/date_time_value_object.py
ddd_value_objects/date_value_object.py
ddd_value_objects/decimal_value_object.py
ddd_value_objects/email_value_object.py
ddd_value_objects/enum_value_object.py
ddd_value_objects/float_value_object.py
ddd_value_objects/int_value_object.py
ddd_value_objects/invalid_argument_error.py
ddd_value_objects/ip_address_value_object.py
ddd_value_objects/money_value_object.py
ddd_value_objects/phone_number_value_object.py
ddd_value_objects/positive_decimal_value_object.py
ddd_value_objects/positive_float_value_object.py
ddd_value_objects/positive_int_value_object.py
ddd_value_objects/string_value_object.py
ddd_value_objects/url_value_object.py
ddd_value_objects/uuid_value_object.py
ddd_value_objects/value_object.py
ddd_value_objects-0.1.7.1.dist-info/licenses/LICENSE
ddd_value_objects-0.1.7.1.dist-info/METADATA
ddd_value_objects-0.1.7.1.dist-info/WHEEL
ddd_value_objects-0.1.7.1.dist-info/top_level.txt
ddd_value_objects-0.1.7.1.dist-info/RECORD
