Metadata-Version: 2.4
Name: ddd-value-objects
Version: 0.1.7.1
Summary: A collection of base classes for Domain-Driven Design (DDD) value objects and entities in Python
License: MIT
Requires-Python: >=3.10
License-File: LICENSE
Dynamic: license-file
